rocket3/__init__.py
rocket3-20240929.2.dist-info/LICENSE.txt
rocket3-20240929.2.dist-info/METADATA
rocket3-20240929.2.dist-info/WHEEL
rocket3-20240929.2.dist-info/top_level.txt
rocket3-20240929.2.dist-info/RECORD
