Metadata-Version: 2.1
Name: rocket3
Version: 20240929.2
Summary: A multi-threaded WSGI compiliant and secure web server
Author-email: Massimo Di Pierro <massimo.dipierro@gmail.com>
Project-URL: Homepage, https://github.com/web2py/rocket3
Project-URL: Bug Tracker, https://github.com/web2py/rocket3/issues
Classifier: Programming Language :: Python :: 3
Classifier: License :: OSI Approved :: BSD License
Classifier: Operating System :: OS Independent
Requires-Python: >=3.7
License-File: LICENSE.txt
